fuzzy_path.py
fuzzy_path-0.1.dist-info/METADATA
fuzzy_path-0.1.dist-info/WHEEL
fuzzy_path-0.1.dist-info/entry_points.txt
fuzzy_path-0.1.dist-info/top_level.txt
fuzzy_path-0.1.dist-info/RECORD
