Metadata-Version: 2.1
Name: fuzzy-path
Version: 0.1
Summary: List paths by chars composed by first letters of each levels
Home-page: https://github.com/weaming/fuzzy-path
Author: weaming
Author-email: garden.yuen@gmail.com
License: UNKNOWN
Project-URL: Source, https://github.com/weaming/fuzzy-path
Project-URL: Bug Reports, https://github.com/weaming/fuzzy-path
Keywords: developer,efficiency
Platform: UNKNOWN
Requires-Dist: filetree (==0.3.5)
